fast_json_normalize/cythonized.cpython-39-x86_64-linux-gnu.so
fast_json_normalize/__init__.py
fast_json_normalize/test_main.py
fast_json_normalize-0.0.9.dist-info/WHEEL
fast_json_normalize-0.0.9.dist-info/LICENSE
fast_json_normalize-0.0.9.dist-info/RECORD
fast_json_normalize-0.0.9.dist-info/top_level.txt
fast_json_normalize-0.0.9.dist-info/METADATA
