Metadata-Version: 2.1
Name: fast-json-normalize
Version: 0.0.9
Summary: Faster pandas json normalize
Home-page: https://github.com/smpurkis/fast_json_normalize
Author: Sam Purkis
Author-email: sam.purkis@hotmail.co.uk
License: UNKNOWN
Platform: UNKNOWN
Classifier: Programming Language :: Python :: 3
Classifier: License :: OSI Approved :: MIT License
Classifier: Operating System :: OS Independent
Requires-Python: >=3.5
Requires-Dist: pytest
Requires-Dist: cython
Requires-Dist: pandas
